setup.py
s3funnel/__init__.py
s3funnel/exceptions.py
s3funnel/jobs.py
s3funnel.egg-info/PKG-INFO
s3funnel.egg-info/SOURCES.txt
s3funnel.egg-info/dependency_links.txt
s3funnel.egg-info/entry_points.txt
s3funnel.egg-info/not-zip-safe
s3funnel.egg-info/requires.txt
s3funnel.egg-info/top_level.txt
scripts/s3funnel