Metadata-Version: 1.0
Name: s3funnel
Version: 0.6.5
Summary: Multithreaded tool for performing operations on Amazon's S3
Home-page: https://github.com/sstoiana/s3funnel
Author: Sorin Stoiana
Author-email: sorinalin.stoiana@gmail.com
License: MIT
Platform: UNKNOWN
